doweb/viewer.py
doweb/config.py
doweb/__init__.py
doweb/custom.css
doweb/server_jupyter.py
doweb/default.py
doweb/py.typed
doweb/layout_server/__init__.cpython-311-darwin.so
doweb/browser/__init__.cpython-311-darwin.so
doweb/static/__init__.py
doweb/static/custom.css
doweb/static/viewer.js
doweb/static/client.css
doweb/static/bootstrap/bootstrap.min.css
doweb/static/bootstrap/bootstrap.bundle.min.js.map
doweb/static/bootstrap/bootstrap.bundle.min.js
doweb/static/bootstrap/__init__.py
doweb/static/bootstrap/bootstrap.min.css.map
doweb/static/bootstrap/bootstrap.min.js
doweb/static/bootstrap/bootstrap.min.js.map
doweb/static/img/doweb.png
doweb/static/img/__init__.py
doweb/api/viewer.py
doweb/api/__init__.py
doweb/api/browser.py
doweb/templates/browser.html
doweb/templates/__init__.py
doweb/templates/viewer.html
doweb/templates/nav.html
doweb-1.7.2.dist-info/RECORD
doweb-1.7.2.dist-info/WHEEL
doweb-1.7.2.dist-info/top_level.txt
doweb-1.7.2.dist-info/METADATA
doweb-1.7.2.dist-info/licenses/LICENSE
