Metadata-Version: 2.4
Name: doweb
Version: 1.7.2
Summary: KLayout API implementation of gdsfactory
Author-email: DoPlayDo <contact@gdsfactory.com>
Classifier: Programming Language :: Python :: 3.11
Classifier: Programming Language :: Python :: 3.12
Classifier: Programming Language :: Python :: 3.13
Classifier: Operating System :: OS Independent
Requires-Python: >=3.11
License-File: LICENSE
Requires-Dist: klayout>=0.29.11
Requires-Dist: fastapi
Requires-Dist: uvicorn[standard]
Requires-Dist: jinja2
Requires-Dist: pydantic_extra_types>=2.6.0
Requires-Dist: pydantic-settings>=2.10.1
Requires-Dist: loguru>=0.7.3
Requires-Dist: pydantic>=2.11.7
Provides-Extra: dev
Requires-Dist: mypy; extra == "dev"
Requires-Dist: pre-commit; extra == "dev"
Requires-Dist: gitpython; extra == "dev"
Requires-Dist: pylsp-mypy; extra == "dev"
Requires-Dist: types-cachetools; extra == "dev"
Requires-Dist: towncrier; extra == "dev"
Requires-Dist: tbump; extra == "dev"
Requires-Dist: cython>=3.1.3; extra == "dev"
Requires-Dist: setuptools>=80.9.0; extra == "dev"
Requires-Dist: ruff>=0.13.1; extra == "dev"
Requires-Dist: pyright>=1.1.405; extra == "dev"
Requires-Dist: websockets>=15.0.1; extra == "dev"
Provides-Extra: docs
Requires-Dist: sphinx; extra == "docs"
Requires-Dist: sphinx_rtd_theme; extra == "docs"
Requires-Dist: sphinxcontrib-video; extra == "docs"
Requires-Dist: sphinx-autodoc-typehints; extra == "docs"
Requires-Dist: sphinx-book-theme==1.1.4; extra == "docs"
Requires-Dist: sphinx-click; extra == "docs"
Requires-Dist: sphinx-copybutton; extra == "docs"
Requires-Dist: sphinx-markdown-tables==0.0.17; extra == "docs"
Requires-Dist: myst-parser; extra == "docs"
Requires-Dist: matplotlib; extra == "docs"
Requires-Dist: nbsphinx; extra == "docs"
Requires-Dist: autodoc_pydantic; extra == "docs"
Provides-Extra: ipy
Requires-Dist: ipython; extra == "ipy"
Requires-Dist: ipywidgets; extra == "ipy"
Requires-Dist: ipyevents; extra == "ipy"
Provides-Extra: tests
Requires-Dist: pytest; extra == "tests"
Requires-Dist: pytest-cov; extra == "tests"
Dynamic: license-file
